infinopy/__init__.py
infinopy/client.py
tests/__init__.py
tests/test_client.py
infinopy-0.0.7.dist-info/METADATA
infinopy-0.0.7.dist-info/WHEEL
infinopy-0.0.7.dist-info/top_level.txt
infinopy-0.0.7.dist-info/RECORD
