Metadata-Version: 2.1
Name: infinopy
Version: 0.0.7
Summary: A Python package for Infino
Home-page: https://github.com/infinohq/infino
Author: Vinay K
Author-email: vinaykakade@gmail.com
Classifier: License :: OSI Approved :: Apache Software License
Classifier: Programming Language :: Python :: 3
Classifier: Programming Language :: Python :: 3.6
Classifier: Programming Language :: Python :: 3.7
Classifier: Programming Language :: Python :: 3.8
Classifier: Programming Language :: Python :: 3.9
Classifier: Programming Language :: Python :: 3.10
Requires-Dist: docker
Requires-Dist: requests
